{"actualizado":"2026-06-11 22:25","total":20230,"tiendas":[{"nombre":"Acuenta","slug":"acuenta","ofertas":194,"actualizado":"2026-06-11 22:25"},{"nombre":"Central Mayorista","slug":"central-mayorista","ofertas":220,"actualizado":"2026-06-11 22:25"},{"nombre":"Falabella","slug":"falabella","ofertas":1419,"actualizado":"2026-06-11 22:25"},{"nombre":"Hites","slug":"hites","ofertas":1738,"actualizado":"2026-06-11 22:25"},{"nombre":"Jumbo","slug":"jumbo","ofertas":1685,"actualizado":"2026-06-11 22:05"},{"nombre":"La Polar","slug":"la-polar","ofertas":875,"actualizado":"2026-06-11 22:25"},{"nombre":"Lider","slug":"lider","ofertas":1145,"actualizado":"2026-06-11 22:25"},{"nombre":"Paris","slug":"paris","ofertas":4633,"actualizado":"2026-06-11 22:25"},{"nombre":"Ripley","slug":"ripley","ofertas":3099,"actualizado":"2026-06-11 22:25"},{"nombre":"Santa Isabel","slug":"santa-isabel","ofertas":1790,"actualizado":"2026-06-11 22:07"},{"nombre":"Super10","slug":"super10","ofertas":26,"actualizado":"2026-06-11 22:25"},{"nombre":"Tottus","slug":"tottus","ofertas":868,"actualizado":"2026-06-11 22:25"},{"nombre":"Unimarc","slug":"unimarc","ofertas":2538,"actualizado":"2026-06-11 22:25"}]}